pybaseconv/__init__.py
pybaseconv/converter.py
pybaseconv-0.0.1.dist-info/METADATA
pybaseconv-0.0.1.dist-info/RECORD
pybaseconv-0.0.1.dist-info/WHEEL
pybaseconv-0.0.1.dist-info/top_level.txt
tests/__init__.py
tests/test_converter.py
