Metadata-Version: 2.1
Name: pybaseconv
Version: 0.0.1
Summary: This library allows you to convert a number from any base to any base
Home-page: UNKNOWN
Author: Samira El Aabidi
Author-email: sam.elaabidi@gmail.com
License: UNKNOWN
Keywords: Python,Base conversion
Platform: UNKNOWN
Classifier: Programming Language :: Python :: 3.5
Classifier: Programming Language :: Python :: 3.6
Classifier: Development Status :: 5 - Production/Stable
Classifier: Intended Audience :: Developers
Classifier: Intended Audience :: Information Technology
Classifier: License :: OSI Approved :: MIT License
Classifier: Natural Language :: English
Classifier: Operating System :: OS Independent
Classifier: Topic :: Software Development :: Libraries :: Python Modules
